[
    {
        "node_id": "MDY6Q29tbWl0MjAwODk4NjA6YWZjNDI4YzVlZTU3MzNhMTczOWQ0MjQ0NWM2ODJjNzhmODg0NGMxZg==",
        "commit": {
            "tree": {
                "sha": "febcdda440ce38958aa1a06553be4ba7e7fa42df",
                "url": "https://api.github.com/repos/apache/portals-pluto/git/trees/febcdda440ce38958aa1a06553be4ba7e7fa42df"
            },
            "author": {
                "email": "neil.griffin.scm@gmail.com",
                "name": "Neil Griffin",
                "date": "2016-09-07T15:30:01.000-04:00"
            },
            "message": "Fixed NPE by using null-safe equals check",
            "committer": {
                "email": "neil.griffin.scm@gmail.com",
                "name": "Neil Griffin",
                "date": "2016-09-07T15:30:01.000-04:00"
            },
            "url": "https://api.github.com/repos/apache/portals-pluto/git/commits/afc428c5ee5733a1739d42445c682c78f8844c1f",
            "comment_count": 0
        },
        "parents": [
            {
                "html_url": "https://github.com/apache/portals-pluto/commit/0000849ea7b7e348e987576c8b05e3a01a89b1dc",
                "sha": "0000849ea7b7e348e987576c8b05e3a01a89b1dc",
                "url": "https://api.github.com/repos/apache/portals-pluto/commits/0000849ea7b7e348e987576c8b05e3a01a89b1dc"
            }
        ],
        "score": 12.831517,
        "url": "https://api.github.com/repos/apache/portals-pluto/commits/afc428c5ee5733a1739d42445c682c78f8844c1f",
        "comments_url": "https://api.github.com/repos/apache/portals-pluto/commits/afc428c5ee5733a1739d42445c682c78f8844c1f/comments",
        "repository": {
            "git_commits_url": "https://api.github.com/repos/apache/portals-pluto/git/commits{/sha}",
            "blobs_url": "https://api.github.com/repos/apache/portals-pluto/git/blobs{/sha}",
            "tags_url": "https://api.github.com/repos/apache/portals-pluto/tags",
            "fork": false,
            "keys_url": "https://api.github.com/repos/apache/portals-pluto/keys{/key_id}",
            "issues_url": "https://api.github.com/repos/apache/portals-pluto/issues{/number}",
            "commits_url": "https://api.github.com/repos/apache/portals-pluto/commits{/sha}",
            "statuses_url": "https://api.github.com/repos/apache/portals-pluto/statuses/{sha}",
            "notifications_url": "https://api.github.com/repos/apache/portals-pluto/notifications{?since,all,participating}",
            "forks_url": "https://api.github.com/repos/apache/portals-pluto/forks",
            "labels_url": "https://api.github.com/repos/apache/portals-pluto/labels{/name}",
            "contributors_url": "https://api.github.com/repos/apache/portals-pluto/contributors",
            "trees_url": "https://api.github.com/repos/apache/portals-pluto/git/trees{/sha}",
            "merges_url": "https://api.github.com/repos/apache/portals-pluto/merges",
            "contents_url": "https://api.github.com/repos/apache/portals-pluto/contents/{+path}",
            "assignees_url": "https://api.github.com/repos/apache/portals-pluto/assignees{/user}",
            "pulls_url": "https://api.github.com/repos/apache/portals-pluto/pulls{/number}",
            "id": 20089860,
            "owner": {
                "gists_url": "https://api.github.com/users/apache/gists{/gist_id}",
                "following_url": "https://api.github.com/users/apache/following{/other_user}",
                "site_admin": false,
                "gravatar_id": "",
                "events_url": "https://api.github.com/users/apache/events{/privacy}",
                "starred_url": "https://api.github.com/users/apache/starred{/owner}{/repo}",
                "followers_url": "https://api.github.com/users/apache/followers",
                "subscriptions_url": "https://api.github.com/users/apache/subscriptions",
                "organizations_url": "https://api.github.com/users/apache/orgs",
                "id": 47359,
                "node_id": "MDEyOk9yZ2FuaXphdGlvbjQ3MzU5",
                "received_events_url": "https://api.github.com/users/apache/received_events",
                "avatar_url": "https://avatars0.githubusercontent.com/u/47359?v=4",
                "login": "apache",
                "html_url": "https://github.com/apache",
                "type": "Organization",
                "repos_url": "https://api.github.com/users/apache/repos",
                "url": "https://api.github.com/users/apache"
            },
            "private": false,
            "deployments_url": "https://api.github.com/repos/apache/portals-pluto/deployments",
            "name": "portals-pluto",
            "subscription_url": "https://api.github.com/repos/apache/portals-pluto/subscription",
            "git_tags_url": "https://api.github.com/repos/apache/portals-pluto/git/tags{/sha}",
            "description": "Mirror of Apache Pluto",
            "url": "https://api.github.com/repos/apache/portals-pluto",
            "events_url": "https://api.github.com/repos/apache/portals-pluto/events",
            "comments_url": "https://api.github.com/repos/apache/portals-pluto/comments{/number}",
            "issue_comment_url": "https://api.github.com/repos/apache/portals-pluto/issues/comments{/number}",
            "milestones_url": "https://api.github.com/repos/apache/portals-pluto/milestones{/number}",
            "node_id": "MDEwOlJlcG9zaXRvcnkyMDA4OTg2MA==",
            "compare_url": "https://api.github.com/repos/apache/portals-pluto/compare/{base}...{head}",
            "html_url": "https://github.com/apache/portals-pluto",
            "git_refs_url": "https://api.github.com/repos/apache/portals-pluto/git/refs{/sha}",
            "issue_events_url": "https://api.github.com/repos/apache/portals-pluto/issues/events{/number}",
            "hooks_url": "https://api.github.com/repos/apache/portals-pluto/hooks",
            "releases_url": "https://api.github.com/repos/apache/portals-pluto/releases{/id}",
            "archive_url": "https://api.github.com/repos/apache/portals-pluto/{archive_format}{/ref}",
            "subscribers_url": "https://api.github.com/repos/apache/portals-pluto/subscribers",
            "collaborators_url": "https://api.github.com/repos/apache/portals-pluto/collaborators{/collaborator}",
            "teams_url": "https://api.github.com/repos/apache/portals-pluto/teams",
            "languages_url": "https://api.github.com/repos/apache/portals-pluto/languages",
            "stargazers_url": "https://api.github.com/repos/apache/portals-pluto/stargazers",
            "branches_url": "https://api.github.com/repos/apache/portals-pluto/branches{/branch}",
            "full_name": "apache/portals-pluto",
            "downloads_url": "https://api.github.com/repos/apache/portals-pluto/downloads"
        },
        "html_url": "https://github.com/apache/portals-pluto/commit/afc428c5ee5733a1739d42445c682c78f8844c1f",
        "committer": {
            "gists_url": "https://api.github.com/users/ngriffin7a/gists{/gist_id}",
            "following_url": "https://api.github.com/users/ngriffin7a/following{/other_user}",
            "site_admin": false,
            "gravatar_id": "",
            "events_url": "https://api.github.com/users/ngriffin7a/events{/privacy}",
            "starred_url": "https://api.github.com/users/ngriffin7a/starred{/owner}{/repo}",
            "followers_url": "https://api.github.com/users/ngriffin7a/followers",
            "subscriptions_url": "https://api.github.com/users/ngriffin7a/subscriptions",
            "organizations_url": "https://api.github.com/users/ngriffin7a/orgs",
            "id": 989387,
            "node_id": "MDQ6VXNlcjk4OTM4Nw==",
            "received_events_url": "https://api.github.com/users/ngriffin7a/received_events",
            "avatar_url": "https://avatars2.githubusercontent.com/u/989387?v=4",
            "login": "ngriffin7a",
            "html_url": "https://github.com/ngriffin7a",
            "type": "User",
            "repos_url": "https://api.github.com/users/ngriffin7a/repos",
            "url": "https://api.github.com/users/ngriffin7a"
        },
        "sha": "afc428c5ee5733a1739d42445c682c78f8844c1f",
        "author": {
            "gists_url": "https://api.github.com/users/ngriffin7a/gists{/gist_id}",
            "following_url": "https://api.github.com/users/ngriffin7a/following{/other_user}",
            "site_admin": false,
            "gravatar_id": "",
            "events_url": "https://api.github.com/users/ngriffin7a/events{/privacy}",
            "starred_url": "https://api.github.com/users/ngriffin7a/starred{/owner}{/repo}",
            "followers_url": "https://api.github.com/users/ngriffin7a/followers",
            "subscriptions_url": "https://api.github.com/users/ngriffin7a/subscriptions",
            "organizations_url": "https://api.github.com/users/ngriffin7a/orgs",
            "id": 989387,
            "node_id": "MDQ6VXNlcjk4OTM4Nw==",
            "received_events_url": "https://api.github.com/users/ngriffin7a/received_events",
            "avatar_url": "https://avatars2.githubusercontent.com/u/989387?v=4",
            "login": "ngriffin7a",
            "html_url": "https://github.com/ngriffin7a",
            "type": "User",
            "repos_url": "https://api.github.com/users/ngriffin7a/repos",
            "url": "https://api.github.com/users/ngriffin7a"
        }
    },
    {
        "node_id": "MDY6Q29tbWl0MjAwODk4NjA6MWU1Zjc0OThiYWE5Mzk5YTM3NzhlYjc1ODEwYzlhZThlZWEwMGRhOA==",
        "commit": {
            "tree": {
                "sha": "71ec8df1f38847107b2b542bdc2537849c006e00",
                "url": "https://api.github.com/repos/apache/portals-pluto/git/trees/71ec8df1f38847107b2b542bdc2537849c006e00"
            },
            "author": {
                "email": "dettborn@apache.org",
                "name": "Torsten Dettborn",
                "date": "2008-01-08T09:10:26.000Z"
            },
            "message": "Fix NullPointerException for the case, when multi values are null.\n\ngit-svn-id: https://svn.apache.org/repos/asf/portals/pluto/trunk@609912 13f79535-47bb-0310-9956-ffa450edef68",
            "committer": {
                "email": "dettborn@apache.org",
                "name": "Torsten Dettborn",
                "date": "2008-01-08T09:10:26.000Z"
            },
            "url": "https://api.github.com/repos/apache/portals-pluto/git/commits/1e5f7498baa9399a3778eb75810c9ae8eea00da8",
            "comment_count": 0
        },
        "parents": [
            {
                "html_url": "https://github.com/apache/portals-pluto/commit/e005855f5a8061b68120ac0ec4982900b2ef3588",
                "sha": "e005855f5a8061b68120ac0ec4982900b2ef3588",
                "url": "https://api.github.com/repos/apache/portals-pluto/commits/e005855f5a8061b68120ac0ec4982900b2ef3588"
            }
        ],
        "score": 11.748931,
        "url": "https://api.github.com/repos/apache/portals-pluto/commits/1e5f7498baa9399a3778eb75810c9ae8eea00da8",
        "comments_url": "https://api.github.com/repos/apache/portals-pluto/commits/1e5f7498baa9399a3778eb75810c9ae8eea00da8/comments",
        "repository": {
            "git_commits_url": "https://api.github.com/repos/apache/portals-pluto/git/commits{/sha}",
            "blobs_url": "https://api.github.com/repos/apache/portals-pluto/git/blobs{/sha}",
            "tags_url": "https://api.github.com/repos/apache/portals-pluto/tags",
            "fork": false,
            "keys_url": "https://api.github.com/repos/apache/portals-pluto/keys{/key_id}",
            "issues_url": "https://api.github.com/repos/apache/portals-pluto/issues{/number}",
            "commits_url": "https://api.github.com/repos/apache/portals-pluto/commits{/sha}",
            "statuses_url": "https://api.github.com/repos/apache/portals-pluto/statuses/{sha}",
            "notifications_url": "https://api.github.com/repos/apache/portals-pluto/notifications{?since,all,participating}",
            "forks_url": "https://api.github.com/repos/apache/portals-pluto/forks",
            "labels_url": "https://api.github.com/repos/apache/portals-pluto/labels{/name}",
            "contributors_url": "https://api.github.com/repos/apache/portals-pluto/contributors",
            "trees_url": "https://api.github.com/repos/apache/portals-pluto/git/trees{/sha}",
            "merges_url": "https://api.github.com/repos/apache/portals-pluto/merges",
            "contents_url": "https://api.github.com/repos/apache/portals-pluto/contents/{+path}",
            "assignees_url": "https://api.github.com/repos/apache/portals-pluto/assignees{/user}",
            "pulls_url": "https://api.github.com/repos/apache/portals-pluto/pulls{/number}",
            "id": 20089860,
            "owner": {
                "gists_url": "https://api.github.com/users/apache/gists{/gist_id}",
                "following_url": "https://api.github.com/users/apache/following{/other_user}",
                "site_admin": false,
                "gravatar_id": "",
                "events_url": "https://api.github.com/users/apache/events{/privacy}",
                "starred_url": "https://api.github.com/users/apache/starred{/owner}{/repo}",
                "followers_url": "https://api.github.com/users/apache/followers",
                "subscriptions_url": "https://api.github.com/users/apache/subscriptions",
                "organizations_url": "https://api.github.com/users/apache/orgs",
                "id": 47359,
                "node_id": "MDEyOk9yZ2FuaXphdGlvbjQ3MzU5",
                "received_events_url": "https://api.github.com/users/apache/received_events",
                "avatar_url": "https://avatars0.githubusercontent.com/u/47359?v=4",
                "login": "apache",
                "html_url": "https://github.com/apache",
                "type": "Organization",
                "repos_url": "https://api.github.com/users/apache/repos",
                "url": "https://api.github.com/users/apache"
            },
            "private": false,
            "deployments_url": "https://api.github.com/repos/apache/portals-pluto/deployments",
            "name": "portals-pluto",
            "subscription_url": "https://api.github.com/repos/apache/portals-pluto/subscription",
            "git_tags_url": "https://api.github.com/repos/apache/portals-pluto/git/tags{/sha}",
            "description": "Mirror of Apache Pluto",
            "url": "https://api.github.com/repos/apache/portals-pluto",
            "events_url": "https://api.github.com/repos/apache/portals-pluto/events",
            "comments_url": "https://api.github.com/repos/apache/portals-pluto/comments{/number}",
            "issue_comment_url": "https://api.github.com/repos/apache/portals-pluto/issues/comments{/number}",
            "milestones_url": "https://api.github.com/repos/apache/portals-pluto/milestones{/number}",
            "node_id": "MDEwOlJlcG9zaXRvcnkyMDA4OTg2MA==",
            "compare_url": "https://api.github.com/repos/apache/portals-pluto/compare/{base}...{head}",
            "html_url": "https://github.com/apache/portals-pluto",
            "git_refs_url": "https://api.github.com/repos/apache/portals-pluto/git/refs{/sha}",
            "issue_events_url": "https://api.github.com/repos/apache/portals-pluto/issues/events{/number}",
            "hooks_url": "https://api.github.com/repos/apache/portals-pluto/hooks",
            "releases_url": "https://api.github.com/repos/apache/portals-pluto/releases{/id}",
            "archive_url": "https://api.github.com/repos/apache/portals-pluto/{archive_format}{/ref}",
            "subscribers_url": "https://api.github.com/repos/apache/portals-pluto/subscribers",
            "collaborators_url": "https://api.github.com/repos/apache/portals-pluto/collaborators{/collaborator}",
            "teams_url": "https://api.github.com/repos/apache/portals-pluto/teams",
            "languages_url": "https://api.github.com/repos/apache/portals-pluto/languages",
            "stargazers_url": "https://api.github.com/repos/apache/portals-pluto/stargazers",
            "branches_url": "https://api.github.com/repos/apache/portals-pluto/branches{/branch}",
            "full_name": "apache/portals-pluto",
            "downloads_url": "https://api.github.com/repos/apache/portals-pluto/downloads"
        },
        "html_url": "https://github.com/apache/portals-pluto/commit/1e5f7498baa9399a3778eb75810c9ae8eea00da8",
        "committer": null,
        "sha": "1e5f7498baa9399a3778eb75810c9ae8eea00da8",
        "author": null
    },
    {
        "node_id": "MDY6Q29tbWl0MjAwODk4NjA6ZmJiOTU4ZjRlYTg1Nzc1M2Q3NTM2OGNlZTMzMDIyMjM4MzAwYjZjNQ==",
        "commit": {
            "tree": {
                "sha": "d6650c34de0e2e2e977e2c0653f363155a0dee56",
                "url": "https://api.github.com/repos/apache/portals-pluto/git/trees/d6650c34de0e2e2e977e2c0653f363155a0dee56"
            },
            "author": {
                "email": "dettborn@apache.org",
                "name": "Torsten Dettborn",
                "date": "2007-12-28T08:42:10.000Z"
            },
            "message": "fix NullpointerException for PortletPreferences\n\ngit-svn-id: https://svn.apache.org/repos/asf/portals/pluto/branches/1.1-286-trunk-merge@607190 13f79535-47bb-0310-9956-ffa450edef68",
            "committer": {
                "email": "dettborn@apache.org",
                "name": "Torsten Dettborn",
                "date": "2007-12-28T08:42:10.000Z"
            },
            "url": "https://api.github.com/repos/apache/portals-pluto/git/commits/fbb958f4ea857753d75368cee33022238300b6c5",
            "comment_count": 0
        },
        "parents": [
            {
                "html_url": "https://github.com/apache/portals-pluto/commit/62c9ef5a6d751e5cfc964081197720eef1c665fb",
                "sha": "62c9ef5a6d751e5cfc964081197720eef1c665fb",
                "url": "https://api.github.com/repos/apache/portals-pluto/commits/62c9ef5a6d751e5cfc964081197720eef1c665fb"
            }
        ],
        "score": 11.748836,
        "url": "https://api.github.com/repos/apache/portals-pluto/commits/fbb958f4ea857753d75368cee33022238300b6c5",
        "comments_url": "https://api.github.com/repos/apache/portals-pluto/commits/fbb958f4ea857753d75368cee33022238300b6c5/comments",
        "repository": {
            "git_commits_url": "https://api.github.com/repos/apache/portals-pluto/git/commits{/sha}",
            "blobs_url": "https://api.github.com/repos/apache/portals-pluto/git/blobs{/sha}",
            "tags_url": "https://api.github.com/repos/apache/portals-pluto/tags",
            "fork": false,
            "keys_url": "https://api.github.com/repos/apache/portals-pluto/keys{/key_id}",
            "issues_url": "https://api.github.com/repos/apache/portals-pluto/issues{/number}",
            "commits_url": "https://api.github.com/repos/apache/portals-pluto/commits{/sha}",
            "statuses_url": "https://api.github.com/repos/apache/portals-pluto/statuses/{sha}",
            "notifications_url": "https://api.github.com/repos/apache/portals-pluto/notifications{?since,all,participating}",
            "forks_url": "https://api.github.com/repos/apache/portals-pluto/forks",
            "labels_url": "https://api.github.com/repos/apache/portals-pluto/labels{/name}",
            "contributors_url": "https://api.github.com/repos/apache/portals-pluto/contributors",
            "trees_url": "https://api.github.com/repos/apache/portals-pluto/git/trees{/sha}",
            "merges_url": "https://api.github.com/repos/apache/portals-pluto/merges",
            "contents_url": "https://api.github.com/repos/apache/portals-pluto/contents/{+path}",
            "assignees_url": "https://api.github.com/repos/apache/portals-pluto/assignees{/user}",
            "pulls_url": "https://api.github.com/repos/apache/portals-pluto/pulls{/number}",
            "id": 20089860,
            "owner": {
                "gists_url": "https://api.github.com/users/apache/gists{/gist_id}",
                "following_url": "https://api.github.com/users/apache/following{/other_user}",
                "site_admin": false,
                "gravatar_id": "",
                "events_url": "https://api.github.com/users/apache/events{/privacy}",
                "starred_url": "https://api.github.com/users/apache/starred{/owner}{/repo}",
                "followers_url": "https://api.github.com/users/apache/followers",
                "subscriptions_url": "https://api.github.com/users/apache/subscriptions",
                "organizations_url": "https://api.github.com/users/apache/orgs",
                "id": 47359,
                "node_id": "MDEyOk9yZ2FuaXphdGlvbjQ3MzU5",
                "received_events_url": "https://api.github.com/users/apache/received_events",
                "avatar_url": "https://avatars0.githubusercontent.com/u/47359?v=4",
                "login": "apache",
                "html_url": "https://github.com/apache",
                "type": "Organization",
                "repos_url": "https://api.github.com/users/apache/repos",
                "url": "https://api.github.com/users/apache"
            },
            "private": false,
            "deployments_url": "https://api.github.com/repos/apache/portals-pluto/deployments",
            "name": "portals-pluto",
            "subscription_url": "https://api.github.com/repos/apache/portals-pluto/subscription",
            "git_tags_url": "https://api.github.com/repos/apache/portals-pluto/git/tags{/sha}",
            "description": "Mirror of Apache Pluto",
            "url": "https://api.github.com/repos/apache/portals-pluto",
            "events_url": "https://api.github.com/repos/apache/portals-pluto/events",
            "comments_url": "https://api.github.com/repos/apache/portals-pluto/comments{/number}",
            "issue_comment_url": "https://api.github.com/repos/apache/portals-pluto/issues/comments{/number}",
            "milestones_url": "https://api.github.com/repos/apache/portals-pluto/milestones{/number}",
            "node_id": "MDEwOlJlcG9zaXRvcnkyMDA4OTg2MA==",
            "compare_url": "https://api.github.com/repos/apache/portals-pluto/compare/{base}...{head}",
            "html_url": "https://github.com/apache/portals-pluto",
            "git_refs_url": "https://api.github.com/repos/apache/portals-pluto/git/refs{/sha}",
            "issue_events_url": "https://api.github.com/repos/apache/portals-pluto/issues/events{/number}",
            "hooks_url": "https://api.github.com/repos/apache/portals-pluto/hooks",
            "releases_url": "https://api.github.com/repos/apache/portals-pluto/releases{/id}",
            "archive_url": "https://api.github.com/repos/apache/portals-pluto/{archive_format}{/ref}",
            "subscribers_url": "https://api.github.com/repos/apache/portals-pluto/subscribers",
            "collaborators_url": "https://api.github.com/repos/apache/portals-pluto/collaborators{/collaborator}",
            "teams_url": "https://api.github.com/repos/apache/portals-pluto/teams",
            "languages_url": "https://api.github.com/repos/apache/portals-pluto/languages",
            "stargazers_url": "https://api.github.com/repos/apache/portals-pluto/stargazers",
            "branches_url": "https://api.github.com/repos/apache/portals-pluto/branches{/branch}",
            "full_name": "apache/portals-pluto",
            "downloads_url": "https://api.github.com/repos/apache/portals-pluto/downloads"
        },
        "html_url": "https://github.com/apache/portals-pluto/commit/fbb958f4ea857753d75368cee33022238300b6c5",
        "committer": null,
        "sha": "fbb958f4ea857753d75368cee33022238300b6c5",
        "author": null
    },
    {
        "node_id": "MDY6Q29tbWl0MjAwODk4NjA6YjRkMGI1NjIzYTIxN2RiZDIwZGVjYjUwY2EwNTZiNDI1MmUyMzcxYQ==",
        "commit": {
            "tree": {
                "sha": "687b21ca05379544fab41e32602dae346286972f",
                "url": "https://api.github.com/repos/apache/portals-pluto/git/trees/687b21ca05379544fab41e32602dae346286972f"
            },
            "author": {
                "email": "zheng@apache.org",
                "name": "Zheng Zhong",
                "date": "2006-02-21T11:14:02.000Z"
            },
            "message": "Fixed NullPointerException in PortletPreferencesImpl.\n\ngit-svn-id: https://svn.apache.org/repos/asf/portals/pluto/trunk@379420 13f79535-47bb-0310-9956-ffa450edef68",
            "committer": {
                "email": "zheng@apache.org",
                "name": "Zheng Zhong",
                "date": "2006-02-21T11:14:02.000Z"
            },
            "url": "https://api.github.com/repos/apache/portals-pluto/git/commits/b4d0b5623a217dbd20decb50ca056b4252e2371a",
            "comment_count": 0
        },
        "parents": [
            {
                "html_url": "https://github.com/apache/portals-pluto/commit/58c82e1767c5b8f5d065f877740882b430c0dc7c",
                "sha": "58c82e1767c5b8f5d065f877740882b430c0dc7c",
                "url": "https://api.github.com/repos/apache/portals-pluto/commits/58c82e1767c5b8f5d065f877740882b430c0dc7c"
            }
        ],
        "score": 11.745571,
        "url": "https://api.github.com/repos/apache/portals-pluto/commits/b4d0b5623a217dbd20decb50ca056b4252e2371a",
        "comments_url": "https://api.github.com/repos/apache/portals-pluto/commits/b4d0b5623a217dbd20decb50ca056b4252e2371a/comments",
        "repository": {
            "git_commits_url": "https://api.github.com/repos/apache/portals-pluto/git/commits{/sha}",
            "blobs_url": "https://api.github.com/repos/apache/portals-pluto/git/blobs{/sha}",
            "tags_url": "https://api.github.com/repos/apache/portals-pluto/tags",
            "fork": false,
            "keys_url": "https://api.github.com/repos/apache/portals-pluto/keys{/key_id}",
            "issues_url": "https://api.github.com/repos/apache/portals-pluto/issues{/number}",
            "commits_url": "https://api.github.com/repos/apache/portals-pluto/commits{/sha}",
            "statuses_url": "https://api.github.com/repos/apache/portals-pluto/statuses/{sha}",
            "notifications_url": "https://api.github.com/repos/apache/portals-pluto/notifications{?since,all,participating}",
            "forks_url": "https://api.github.com/repos/apache/portals-pluto/forks",
            "labels_url": "https://api.github.com/repos/apache/portals-pluto/labels{/name}",
            "contributors_url": "https://api.github.com/repos/apache/portals-pluto/contributors",
            "trees_url": "https://api.github.com/repos/apache/portals-pluto/git/trees{/sha}",
            "merges_url": "https://api.github.com/repos/apache/portals-pluto/merges",
            "contents_url": "https://api.github.com/repos/apache/portals-pluto/contents/{+path}",
            "assignees_url": "https://api.github.com/repos/apache/portals-pluto/assignees{/user}",
            "pulls_url": "https://api.github.com/repos/apache/portals-pluto/pulls{/number}",
            "id": 20089860,
            "owner": {
                "gists_url": "https://api.github.com/users/apache/gists{/gist_id}",
                "following_url": "https://api.github.com/users/apache/following{/other_user}",
                "site_admin": false,
                "gravatar_id": "",
                "events_url": "https://api.github.com/users/apache/events{/privacy}",
                "starred_url": "https://api.github.com/users/apache/starred{/owner}{/repo}",
                "followers_url": "https://api.github.com/users/apache/followers",
                "subscriptions_url": "https://api.github.com/users/apache/subscriptions",
                "organizations_url": "https://api.github.com/users/apache/orgs",
                "id": 47359,
                "node_id": "MDEyOk9yZ2FuaXphdGlvbjQ3MzU5",
                "received_events_url": "https://api.github.com/users/apache/received_events",
                "avatar_url": "https://avatars0.githubusercontent.com/u/47359?v=4",
                "login": "apache",
                "html_url": "https://github.com/apache",
                "type": "Organization",
                "repos_url": "https://api.github.com/users/apache/repos",
                "url": "https://api.github.com/users/apache"
            },
            "private": false,
            "deployments_url": "https://api.github.com/repos/apache/portals-pluto/deployments",
            "name": "portals-pluto",
            "subscription_url": "https://api.github.com/repos/apache/portals-pluto/subscription",
            "git_tags_url": "https://api.github.com/repos/apache/portals-pluto/git/tags{/sha}",
            "description": "Mirror of Apache Pluto",
            "url": "https://api.github.com/repos/apache/portals-pluto",
            "events_url": "https://api.github.com/repos/apache/portals-pluto/events",
            "comments_url": "https://api.github.com/repos/apache/portals-pluto/comments{/number}",
            "issue_comment_url": "https://api.github.com/repos/apache/portals-pluto/issues/comments{/number}",
            "milestones_url": "https://api.github.com/repos/apache/portals-pluto/milestones{/number}",
            "node_id": "MDEwOlJlcG9zaXRvcnkyMDA4OTg2MA==",
            "compare_url": "https://api.github.com/repos/apache/portals-pluto/compare/{base}...{head}",
            "html_url": "https://github.com/apache/portals-pluto",
            "git_refs_url": "https://api.github.com/repos/apache/portals-pluto/git/refs{/sha}",
            "issue_events_url": "https://api.github.com/repos/apache/portals-pluto/issues/events{/number}",
            "hooks_url": "https://api.github.com/repos/apache/portals-pluto/hooks",
            "releases_url": "https://api.github.com/repos/apache/portals-pluto/releases{/id}",
            "archive_url": "https://api.github.com/repos/apache/portals-pluto/{archive_format}{/ref}",
            "subscribers_url": "https://api.github.com/repos/apache/portals-pluto/subscribers",
            "collaborators_url": "https://api.github.com/repos/apache/portals-pluto/collaborators{/collaborator}",
            "teams_url": "https://api.github.com/repos/apache/portals-pluto/teams",
            "languages_url": "https://api.github.com/repos/apache/portals-pluto/languages",
            "stargazers_url": "https://api.github.com/repos/apache/portals-pluto/stargazers",
            "branches_url": "https://api.github.com/repos/apache/portals-pluto/branches{/branch}",
            "full_name": "apache/portals-pluto",
            "downloads_url": "https://api.github.com/repos/apache/portals-pluto/downloads"
        },
        "html_url": "https://github.com/apache/portals-pluto/commit/b4d0b5623a217dbd20decb50ca056b4252e2371a",
        "committer": null,
        "sha": "b4d0b5623a217dbd20decb50ca056b4252e2371a",
        "author": null
    },
    {
        "node_id": "MDY6Q29tbWl0MjAwODk4NjA6NjVmN2E5Mjg2ZDcwOTdkNDY1ZGM5Mjk3ODYxNGFiMzEzZjk3OTVkNA==",
        "commit": {
            "tree": {
                "sha": "52dabad7c2f86cb492f7defb4e8fdccb204c015c",
                "url": "https://api.github.com/repos/apache/portals-pluto/git/trees/52dabad7c2f86cb492f7defb4e8fdccb204c015c"
            },
            "author": {
                "email": "esm@apache.org",
                "name": "Elliot Metsger",
                "date": "2006-09-13T21:29:05.000Z"
            },
            "message": "[PLUTO-233]: Fixed an NPE related to PLUTO-233.  initSupportedModesService() threw an NPE because the ServletContext hasn't been initalized.\n\ngit-svn-id: https://svn.apache.org/repos/asf/portals/pluto/trunk@443130 13f79535-47bb-0310-9956-ffa450edef68",
            "committer": {
                "email": "esm@apache.org",
                "name": "Elliot Metsger",
                "date": "2006-09-13T21:29:05.000Z"
            },
            "url": "https://api.github.com/repos/apache/portals-pluto/git/commits/65f7a9286d7097d465dc92978614ab313f9795d4",
            "comment_count": 0
        },
        "parents": [
            {
                "html_url": "https://github.com/apache/portals-pluto/commit/0b3b4fb04f37c1198f6e494421f1f529fb2b0a8b",
                "sha": "0b3b4fb04f37c1198f6e494421f1f529fb2b0a8b",
                "url": "https://api.github.com/repos/apache/portals-pluto/commits/0b3b4fb04f37c1198f6e494421f1f529fb2b0a8b"
            }
        ],
        "score": 10.887759,
        "url": "https://api.github.com/repos/apache/portals-pluto/commits/65f7a9286d7097d465dc92978614ab313f9795d4",
        "comments_url": "https://api.github.com/repos/apache/portals-pluto/commits/65f7a9286d7097d465dc92978614ab313f9795d4/comments",
        "repository": {
            "git_commits_url": "https://api.github.com/repos/apache/portals-pluto/git/commits{/sha}",
            "blobs_url": "https://api.github.com/repos/apache/portals-pluto/git/blobs{/sha}",
            "tags_url": "https://api.github.com/repos/apache/portals-pluto/tags",
            "fork": false,
            "keys_url": "https://api.github.com/repos/apache/portals-pluto/keys{/key_id}",
            "issues_url": "https://api.github.com/repos/apache/portals-pluto/issues{/number}",
            "commits_url": "https://api.github.com/repos/apache/portals-pluto/commits{/sha}",
            "statuses_url": "https://api.github.com/repos/apache/portals-pluto/statuses/{sha}",
            "notifications_url": "https://api.github.com/repos/apache/portals-pluto/notifications{?since,all,participating}",
            "forks_url": "https://api.github.com/repos/apache/portals-pluto/forks",
            "labels_url": "https://api.github.com/repos/apache/portals-pluto/labels{/name}",
            "contributors_url": "https://api.github.com/repos/apache/portals-pluto/contributors",
            "trees_url": "https://api.github.com/repos/apache/portals-pluto/git/trees{/sha}",
            "merges_url": "https://api.github.com/repos/apache/portals-pluto/merges",
            "contents_url": "https://api.github.com/repos/apache/portals-pluto/contents/{+path}",
            "assignees_url": "https://api.github.com/repos/apache/portals-pluto/assignees{/user}",
            "pulls_url": "https://api.github.com/repos/apache/portals-pluto/pulls{/number}",
            "id": 20089860,
            "owner": {
                "gists_url": "https://api.github.com/users/apache/gists{/gist_id}",
                "following_url": "https://api.github.com/users/apache/following{/other_user}",
                "site_admin": false,
                "gravatar_id": "",
                "events_url": "https://api.github.com/users/apache/events{/privacy}",
                "starred_url": "https://api.github.com/users/apache/starred{/owner}{/repo}",
                "followers_url": "https://api.github.com/users/apache/followers",
                "subscriptions_url": "https://api.github.com/users/apache/subscriptions",
                "organizations_url": "https://api.github.com/users/apache/orgs",
                "id": 47359,
                "node_id": "MDEyOk9yZ2FuaXphdGlvbjQ3MzU5",
                "received_events_url": "https://api.github.com/users/apache/received_events",
                "avatar_url": "https://avatars0.githubusercontent.com/u/47359?v=4",
                "login": "apache",
                "html_url": "https://github.com/apache",
                "type": "Organization",
                "repos_url": "https://api.github.com/users/apache/repos",
                "url": "https://api.github.com/users/apache"
            },
            "private": false,
            "deployments_url": "https://api.github.com/repos/apache/portals-pluto/deployments",
            "name": "portals-pluto",
            "subscription_url": "https://api.github.com/repos/apache/portals-pluto/subscription",
            "git_tags_url": "https://api.github.com/repos/apache/portals-pluto/git/tags{/sha}",
            "description": "Mirror of Apache Pluto",
            "url": "https://api.github.com/repos/apache/portals-pluto",
            "events_url": "https://api.github.com/repos/apache/portals-pluto/events",
            "comments_url": "https://api.github.com/repos/apache/portals-pluto/comments{/number}",
            "issue_comment_url": "https://api.github.com/repos/apache/portals-pluto/issues/comments{/number}",
            "milestones_url": "https://api.github.com/repos/apache/portals-pluto/milestones{/number}",
            "node_id": "MDEwOlJlcG9zaXRvcnkyMDA4OTg2MA==",
            "compare_url": "https://api.github.com/repos/apache/portals-pluto/compare/{base}...{head}",
            "html_url": "https://github.com/apache/portals-pluto",
            "git_refs_url": "https://api.github.com/repos/apache/portals-pluto/git/refs{/sha}",
            "issue_events_url": "https://api.github.com/repos/apache/portals-pluto/issues/events{/number}",
            "hooks_url": "https://api.github.com/repos/apache/portals-pluto/hooks",
            "releases_url": "https://api.github.com/repos/apache/portals-pluto/releases{/id}",
            "archive_url": "https://api.github.com/repos/apache/portals-pluto/{archive_format}{/ref}",
            "subscribers_url": "https://api.github.com/repos/apache/portals-pluto/subscribers",
            "collaborators_url": "https://api.github.com/repos/apache/portals-pluto/collaborators{/collaborator}",
            "teams_url": "https://api.github.com/repos/apache/portals-pluto/teams",
            "languages_url": "https://api.github.com/repos/apache/portals-pluto/languages",
            "stargazers_url": "https://api.github.com/repos/apache/portals-pluto/stargazers",
            "branches_url": "https://api.github.com/repos/apache/portals-pluto/branches{/branch}",
            "full_name": "apache/portals-pluto",
            "downloads_url": "https://api.github.com/repos/apache/portals-pluto/downloads"
        },
        "html_url": "https://github.com/apache/portals-pluto/commit/65f7a9286d7097d465dc92978614ab313f9795d4",
        "committer": null,
        "sha": "65f7a9286d7097d465dc92978614ab313f9795d4",
        "author": null
    },
    {
        "node_id": "MDY6Q29tbWl0MjAwODk4NjA6NzBiMGNmYzg2YjM1ODkwMWNjOTNiYmFkNmI3OWVhNTZmMDk4YjliOA==",
        "commit": {
            "tree": {
                "sha": "d3e61f69713dfc872430c8d9a6d78153bfb5e3cd",
                "url": "https://api.github.com/repos/apache/portals-pluto/git/trees/d3e61f69713dfc872430c8d9a6d78153bfb5e3cd"
            },
            "author": {
                "email": "edalquist@apache.org",
                "name": "Eric Dalquist",
                "date": "2010-10-27T00:09:59.000Z"
            },
            "message": "PLUTO-601 Throw IOException instead of NullPointerException when passed a null InputStream to keep functionality consistent between releases.\n\ngit-svn-id: https://svn.apache.org/repos/asf/portals/pluto/trunk@1027780 13f79535-47bb-0310-9956-ffa450edef68",
            "committer": {
                "email": "edalquist@apache.org",
                "name": "Eric Dalquist",
                "date": "2010-10-27T00:09:59.000Z"
            },
            "url": "https://api.github.com/repos/apache/portals-pluto/git/commits/70b0cfc86b358901cc93bbad6b79ea56f098b9b8",
            "comment_count": 0
        },
        "parents": [
            {
                "html_url": "https://github.com/apache/portals-pluto/commit/db941c8775b192f53ff58e7ee8585cade3c88517",
                "sha": "db941c8775b192f53ff58e7ee8585cade3c88517",
                "url": "https://api.github.com/repos/apache/portals-pluto/commits/db941c8775b192f53ff58e7ee8585cade3c88517"
            }
        ],
        "score": 10.600297,
        "url": "https://api.github.com/repos/apache/portals-pluto/commits/70b0cfc86b358901cc93bbad6b79ea56f098b9b8",
        "comments_url": "https://api.github.com/repos/apache/portals-pluto/commits/70b0cfc86b358901cc93bbad6b79ea56f098b9b8/comments",
        "repository": {
            "git_commits_url": "https://api.github.com/repos/apache/portals-pluto/git/commits{/sha}",
            "blobs_url": "https://api.github.com/repos/apache/portals-pluto/git/blobs{/sha}",
            "tags_url": "https://api.github.com/repos/apache/portals-pluto/tags",
            "fork": false,
            "keys_url": "https://api.github.com/repos/apache/portals-pluto/keys{/key_id}",
            "issues_url": "https://api.github.com/repos/apache/portals-pluto/issues{/number}",
            "commits_url": "https://api.github.com/repos/apache/portals-pluto/commits{/sha}",
            "statuses_url": "https://api.github.com/repos/apache/portals-pluto/statuses/{sha}",
            "notifications_url": "https://api.github.com/repos/apache/portals-pluto/notifications{?since,all,participating}",
            "forks_url": "https://api.github.com/repos/apache/portals-pluto/forks",
            "labels_url": "https://api.github.com/repos/apache/portals-pluto/labels{/name}",
            "contributors_url": "https://api.github.com/repos/apache/portals-pluto/contributors",
            "trees_url": "https://api.github.com/repos/apache/portals-pluto/git/trees{/sha}",
            "merges_url": "https://api.github.com/repos/apache/portals-pluto/merges",
            "contents_url": "https://api.github.com/repos/apache/portals-pluto/contents/{+path}",
            "assignees_url": "https://api.github.com/repos/apache/portals-pluto/assignees{/user}",
            "pulls_url": "https://api.github.com/repos/apache/portals-pluto/pulls{/number}",
            "id": 20089860,
            "owner": {
                "gists_url": "https://api.github.com/users/apache/gists{/gist_id}",
                "following_url": "https://api.github.com/users/apache/following{/other_user}",
                "site_admin": false,
                "gravatar_id": "",
                "events_url": "https://api.github.com/users/apache/events{/privacy}",
                "starred_url": "https://api.github.com/users/apache/starred{/owner}{/repo}",
                "followers_url": "https://api.github.com/users/apache/followers",
                "subscriptions_url": "https://api.github.com/users/apache/subscriptions",
                "organizations_url": "https://api.github.com/users/apache/orgs",
                "id": 47359,
                "node_id": "MDEyOk9yZ2FuaXphdGlvbjQ3MzU5",
                "received_events_url": "https://api.github.com/users/apache/received_events",
                "avatar_url": "https://avatars0.githubusercontent.com/u/47359?v=4",
                "login": "apache",
                "html_url": "https://github.com/apache",
                "type": "Organization",
                "repos_url": "https://api.github.com/users/apache/repos",
                "url": "https://api.github.com/users/apache"
            },
            "private": false,
            "deployments_url": "https://api.github.com/repos/apache/portals-pluto/deployments",
            "name": "portals-pluto",
            "subscription_url": "https://api.github.com/repos/apache/portals-pluto/subscription",
            "git_tags_url": "https://api.github.com/repos/apache/portals-pluto/git/tags{/sha}",
            "description": "Mirror of Apache Pluto",
            "url": "https://api.github.com/repos/apache/portals-pluto",
            "events_url": "https://api.github.com/repos/apache/portals-pluto/events",
            "comments_url": "https://api.github.com/repos/apache/portals-pluto/comments{/number}",
            "issue_comment_url": "https://api.github.com/repos/apache/portals-pluto/issues/comments{/number}",
            "milestones_url": "https://api.github.com/repos/apache/portals-pluto/milestones{/number}",
            "node_id": "MDEwOlJlcG9zaXRvcnkyMDA4OTg2MA==",
            "compare_url": "https://api.github.com/repos/apache/portals-pluto/compare/{base}...{head}",
            "html_url": "https://github.com/apache/portals-pluto",
            "git_refs_url": "https://api.github.com/repos/apache/portals-pluto/git/refs{/sha}",
            "issue_events_url": "https://api.github.com/repos/apache/portals-pluto/issues/events{/number}",
            "hooks_url": "https://api.github.com/repos/apache/portals-pluto/hooks",
            "releases_url": "https://api.github.com/repos/apache/portals-pluto/releases{/id}",
            "archive_url": "https://api.github.com/repos/apache/portals-pluto/{archive_format}{/ref}",
            "subscribers_url": "https://api.github.com/repos/apache/portals-pluto/subscribers",
            "collaborators_url": "https://api.github.com/repos/apache/portals-pluto/collaborators{/collaborator}",
            "teams_url": "https://api.github.com/repos/apache/portals-pluto/teams",
            "languages_url": "https://api.github.com/repos/apache/portals-pluto/languages",
            "stargazers_url": "https://api.github.com/repos/apache/portals-pluto/stargazers",
            "branches_url": "https://api.github.com/repos/apache/portals-pluto/branches{/branch}",
            "full_name": "apache/portals-pluto",
            "downloads_url": "https://api.github.com/repos/apache/portals-pluto/downloads"
        },
        "html_url": "https://github.com/apache/portals-pluto/commit/70b0cfc86b358901cc93bbad6b79ea56f098b9b8",
        "committer": null,
        "sha": "70b0cfc86b358901cc93bbad6b79ea56f098b9b8",
        "author": null
    },
    {
        "node_id": "MDY6Q29tbWl0MjAwODk4NjA6ZDc3NDgxYmNkZTk0ZWI3MzJmNWZmY2I4YzU5OTkwMzFjMWEyZjg1Zg==",
        "commit": {
            "tree": {
                "sha": "95157b4145c971c5c95066744974edb0c66ba8b0",
                "url": "https://api.github.com/repos/apache/portals-pluto/git/trees/95157b4145c971c5c95066744974edb0c66ba8b0"
            },
            "author": {
                "email": "ate@apache.org",
                "name": "Ate Douma",
                "date": "2008-10-27T13:35:41.000Z"
            },
            "message": "prevent possible NPE when no Listeners are created yet\n\ngit-svn-id: https://svn.apache.org/repos/asf/portals/pluto/branches/2.0-spi-refactoring@708171 13f79535-47bb-0310-9956-ffa450edef68",
            "committer": {
                "email": "ate@apache.org",
                "name": "Ate Douma",
                "date": "2008-10-27T13:35:41.000Z"
            },
            "url": "https://api.github.com/repos/apache/portals-pluto/git/commits/d77481bcde94eb732f5ffcb8c5999031c1a2f85f",
            "comment_count": 0
        },
        "parents": [
            {
                "html_url": "https://github.com/apache/portals-pluto/commit/c93b6e80b173980c22444c52d7debdf08e1021e2",
                "sha": "c93b6e80b173980c22444c52d7debdf08e1021e2",
                "url": "https://api.github.com/repos/apache/portals-pluto/commits/c93b6e80b173980c22444c52d7debdf08e1021e2"
            }
        ],
        "score": 8.265587,
        "url": "https://api.github.com/repos/apache/portals-pluto/commits/d77481bcde94eb732f5ffcb8c5999031c1a2f85f",
        "comments_url": "https://api.github.com/repos/apache/portals-pluto/commits/d77481bcde94eb732f5ffcb8c5999031c1a2f85f/comments",
        "repository": {
            "git_commits_url": "https://api.github.com/repos/apache/portals-pluto/git/commits{/sha}",
            "blobs_url": "https://api.github.com/repos/apache/portals-pluto/git/blobs{/sha}",
            "tags_url": "https://api.github.com/repos/apache/portals-pluto/tags",
            "fork": false,
            "keys_url": "https://api.github.com/repos/apache/portals-pluto/keys{/key_id}",
            "issues_url": "https://api.github.com/repos/apache/portals-pluto/issues{/number}",
            "commits_url": "https://api.github.com/repos/apache/portals-pluto/commits{/sha}",
            "statuses_url": "https://api.github.com/repos/apache/portals-pluto/statuses/{sha}",
            "notifications_url": "https://api.github.com/repos/apache/portals-pluto/notifications{?since,all,participating}",
            "forks_url": "https://api.github.com/repos/apache/portals-pluto/forks",
            "labels_url": "https://api.github.com/repos/apache/portals-pluto/labels{/name}",
            "contributors_url": "https://api.github.com/repos/apache/portals-pluto/contributors",
            "trees_url": "https://api.github.com/repos/apache/portals-pluto/git/trees{/sha}",
            "merges_url": "https://api.github.com/repos/apache/portals-pluto/merges",
            "contents_url": "https://api.github.com/repos/apache/portals-pluto/contents/{+path}",
            "assignees_url": "https://api.github.com/repos/apache/portals-pluto/assignees{/user}",
            "pulls_url": "https://api.github.com/repos/apache/portals-pluto/pulls{/number}",
            "id": 20089860,
            "owner": {
                "gists_url": "https://api.github.com/users/apache/gists{/gist_id}",
                "following_url": "https://api.github.com/users/apache/following{/other_user}",
                "site_admin": false,
                "gravatar_id": "",
                "events_url": "https://api.github.com/users/apache/events{/privacy}",
                "starred_url": "https://api.github.com/users/apache/starred{/owner}{/repo}",
                "followers_url": "https://api.github.com/users/apache/followers",
                "subscriptions_url": "https://api.github.com/users/apache/subscriptions",
                "organizations_url": "https://api.github.com/users/apache/orgs",
                "id": 47359,
                "node_id": "MDEyOk9yZ2FuaXphdGlvbjQ3MzU5",
                "received_events_url": "https://api.github.com/users/apache/received_events",
                "avatar_url": "https://avatars0.githubusercontent.com/u/47359?v=4",
                "login": "apache",
                "html_url": "https://github.com/apache",
                "type": "Organization",
                "repos_url": "https://api.github.com/users/apache/repos",
                "url": "https://api.github.com/users/apache"
            },
            "private": false,
            "deployments_url": "https://api.github.com/repos/apache/portals-pluto/deployments",
            "name": "portals-pluto",
            "subscription_url": "https://api.github.com/repos/apache/portals-pluto/subscription",
            "git_tags_url": "https://api.github.com/repos/apache/portals-pluto/git/tags{/sha}",
            "description": "Mirror of Apache Pluto",
            "url": "https://api.github.com/repos/apache/portals-pluto",
            "events_url": "https://api.github.com/repos/apache/portals-pluto/events",
            "comments_url": "https://api.github.com/repos/apache/portals-pluto/comments{/number}",
            "issue_comment_url": "https://api.github.com/repos/apache/portals-pluto/issues/comments{/number}",
            "milestones_url": "https://api.github.com/repos/apache/portals-pluto/milestones{/number}",
            "node_id": "MDEwOlJlcG9zaXRvcnkyMDA4OTg2MA==",
            "compare_url": "https://api.github.com/repos/apache/portals-pluto/compare/{base}...{head}",
            "html_url": "https://github.com/apache/portals-pluto",
            "git_refs_url": "https://api.github.com/repos/apache/portals-pluto/git/refs{/sha}",
            "issue_events_url": "https://api.github.com/repos/apache/portals-pluto/issues/events{/number}",
            "hooks_url": "https://api.github.com/repos/apache/portals-pluto/hooks",
            "releases_url": "https://api.github.com/repos/apache/portals-pluto/releases{/id}",
            "archive_url": "https://api.github.com/repos/apache/portals-pluto/{archive_format}{/ref}",
            "subscribers_url": "https://api.github.com/repos/apache/portals-pluto/subscribers",
            "collaborators_url": "https://api.github.com/repos/apache/portals-pluto/collaborators{/collaborator}",
            "teams_url": "https://api.github.com/repos/apache/portals-pluto/teams",
            "languages_url": "https://api.github.com/repos/apache/portals-pluto/languages",
            "stargazers_url": "https://api.github.com/repos/apache/portals-pluto/stargazers",
            "branches_url": "https://api.github.com/repos/apache/portals-pluto/branches{/branch}",
            "full_name": "apache/portals-pluto",
            "downloads_url": "https://api.github.com/repos/apache/portals-pluto/downloads"
        },
        "html_url": "https://github.com/apache/portals-pluto/commit/d77481bcde94eb732f5ffcb8c5999031c1a2f85f",
        "committer": {
            "gists_url": "https://api.github.com/users/ate/gists{/gist_id}",
            "following_url": "https://api.github.com/users/ate/following{/other_user}",
            "site_admin": false,
            "gravatar_id": "",
            "events_url": "https://api.github.com/users/ate/events{/privacy}",
            "starred_url": "https://api.github.com/users/ate/starred{/owner}{/repo}",
            "followers_url": "https://api.github.com/users/ate/followers",
            "subscriptions_url": "https://api.github.com/users/ate/subscriptions",
            "organizations_url": "https://api.github.com/users/ate/orgs",
            "id": 1111320,
            "node_id": "MDQ6VXNlcjExMTEzMjA=",
            "received_events_url": "https://api.github.com/users/ate/received_events",
            "avatar_url": "https://avatars2.githubusercontent.com/u/1111320?v=4",
            "login": "ate",
            "html_url": "https://github.com/ate",
            "type": "User",
            "repos_url": "https://api.github.com/users/ate/repos",
            "url": "https://api.github.com/users/ate"
        },
        "sha": "d77481bcde94eb732f5ffcb8c5999031c1a2f85f",
        "author": {
            "gists_url": "https://api.github.com/users/ate/gists{/gist_id}",
            "following_url": "https://api.github.com/users/ate/following{/other_user}",
            "site_admin": false,
            "gravatar_id": "",
            "events_url": "https://api.github.com/users/ate/events{/privacy}",
            "starred_url": "https://api.github.com/users/ate/starred{/owner}{/repo}",
            "followers_url": "https://api.github.com/users/ate/followers",
            "subscriptions_url": "https://api.github.com/users/ate/subscriptions",
            "organizations_url": "https://api.github.com/users/ate/orgs",
            "id": 1111320,
            "node_id": "MDQ6VXNlcjExMTEzMjA=",
            "received_events_url": "https://api.github.com/users/ate/received_events",
            "avatar_url": "https://avatars2.githubusercontent.com/u/1111320?v=4",
            "login": "ate",
            "html_url": "https://github.com/ate",
            "type": "User",
            "repos_url": "https://api.github.com/users/ate/repos",
            "url": "https://api.github.com/users/ate"
        }
    },
    {
        "node_id": "MDY6Q29tbWl0MjAwODk4NjA6MDc4NjAzZmZlYjMxNTQwNjNlMDY5MTIzZGY5OGM4NDI3MTJjOWRmZg==",
        "commit": {
            "tree": {
                "sha": "a7a07465d2e32ed1fc9ffdd6efb349082e46de57",
                "url": "https://api.github.com/repos/apache/portals-pluto/git/trees/a7a07465d2e32ed1fc9ffdd6efb349082e46de57"
            },
            "author": {
                "email": "cdoremus@apache.org",
                "name": "Craig Doremus",
                "date": "2007-12-08T11:51:51.000Z"
            },
            "message": "Copied from trunk to fix NPE at pluto startup (again!!)\n\ngit-svn-id: https://svn.apache.org/repos/asf/portals/pluto/branches/1.1-286-trunk-merge@602455 13f79535-47bb-0310-9956-ffa450edef68",
            "committer": {
                "email": "cdoremus@apache.org",
                "name": "Craig Doremus",
                "date": "2007-12-08T11:51:51.000Z"
            },
            "url": "https://api.github.com/repos/apache/portals-pluto/git/commits/078603ffeb3154063e069123df98c842712c9dff",
            "comment_count": 0
        },
        "parents": [
            {
                "html_url": "https://github.com/apache/portals-pluto/commit/25afdb3a20f53604a7823ab1b26801ad2452603d",
                "sha": "25afdb3a20f53604a7823ab1b26801ad2452603d",
                "url": "https://api.github.com/repos/apache/portals-pluto/commits/25afdb3a20f53604a7823ab1b26801ad2452603d"
            }
        ],
        "score": 8.261887,
        "url": "https://api.github.com/repos/apache/portals-pluto/commits/078603ffeb3154063e069123df98c842712c9dff",
        "comments_url": "https://api.github.com/repos/apache/portals-pluto/commits/078603ffeb3154063e069123df98c842712c9dff/comments",
        "repository": {
            "git_commits_url": "https://api.github.com/repos/apache/portals-pluto/git/commits{/sha}",
            "blobs_url": "https://api.github.com/repos/apache/portals-pluto/git/blobs{/sha}",
            "tags_url": "https://api.github.com/repos/apache/portals-pluto/tags",
            "fork": false,
            "keys_url": "https://api.github.com/repos/apache/portals-pluto/keys{/key_id}",
            "issues_url": "https://api.github.com/repos/apache/portals-pluto/issues{/number}",
            "commits_url": "https://api.github.com/repos/apache/portals-pluto/commits{/sha}",
            "statuses_url": "https://api.github.com/repos/apache/portals-pluto/statuses/{sha}",
            "notifications_url": "https://api.github.com/repos/apache/portals-pluto/notifications{?since,all,participating}",
            "forks_url": "https://api.github.com/repos/apache/portals-pluto/forks",
            "labels_url": "https://api.github.com/repos/apache/portals-pluto/labels{/name}",
            "contributors_url": "https://api.github.com/repos/apache/portals-pluto/contributors",
            "trees_url": "https://api.github.com/repos/apache/portals-pluto/git/trees{/sha}",
            "merges_url": "https://api.github.com/repos/apache/portals-pluto/merges",
            "contents_url": "https://api.github.com/repos/apache/portals-pluto/contents/{+path}",
            "assignees_url": "https://api.github.com/repos/apache/portals-pluto/assignees{/user}",
            "pulls_url": "https://api.github.com/repos/apache/portals-pluto/pulls{/number}",
            "id": 20089860,
            "owner": {
                "gists_url": "https://api.github.com/users/apache/gists{/gist_id}",
                "following_url": "https://api.github.com/users/apache/following{/other_user}",
                "site_admin": false,
                "gravatar_id": "",
                "events_url": "https://api.github.com/users/apache/events{/privacy}",
                "starred_url": "https://api.github.com/users/apache/starred{/owner}{/repo}",
                "followers_url": "https://api.github.com/users/apache/followers",
                "subscriptions_url": "https://api.github.com/users/apache/subscriptions",
                "organizations_url": "https://api.github.com/users/apache/orgs",
                "id": 47359,
                "node_id": "MDEyOk9yZ2FuaXphdGlvbjQ3MzU5",
                "received_events_url": "https://api.github.com/users/apache/received_events",
                "avatar_url": "https://avatars0.githubusercontent.com/u/47359?v=4",
                "login": "apache",
                "html_url": "https://github.com/apache",
                "type": "Organization",
                "repos_url": "https://api.github.com/users/apache/repos",
                "url": "https://api.github.com/users/apache"
            },
            "private": false,
            "deployments_url": "https://api.github.com/repos/apache/portals-pluto/deployments",
            "name": "portals-pluto",
            "subscription_url": "https://api.github.com/repos/apache/portals-pluto/subscription",
            "git_tags_url": "https://api.github.com/repos/apache/portals-pluto/git/tags{/sha}",
            "description": "Mirror of Apache Pluto",
            "url": "https://api.github.com/repos/apache/portals-pluto",
            "events_url": "https://api.github.com/repos/apache/portals-pluto/events",
            "comments_url": "https://api.github.com/repos/apache/portals-pluto/comments{/number}",
            "issue_comment_url": "https://api.github.com/repos/apache/portals-pluto/issues/comments{/number}",
            "milestones_url": "https://api.github.com/repos/apache/portals-pluto/milestones{/number}",
            "node_id": "MDEwOlJlcG9zaXRvcnkyMDA4OTg2MA==",
            "compare_url": "https://api.github.com/repos/apache/portals-pluto/compare/{base}...{head}",
            "html_url": "https://github.com/apache/portals-pluto",
            "git_refs_url": "https://api.github.com/repos/apache/portals-pluto/git/refs{/sha}",
            "issue_events_url": "https://api.github.com/repos/apache/portals-pluto/issues/events{/number}",
            "hooks_url": "https://api.github.com/repos/apache/portals-pluto/hooks",
            "releases_url": "https://api.github.com/repos/apache/portals-pluto/releases{/id}",
            "archive_url": "https://api.github.com/repos/apache/portals-pluto/{archive_format}{/ref}",
            "subscribers_url": "https://api.github.com/repos/apache/portals-pluto/subscribers",
            "collaborators_url": "https://api.github.com/repos/apache/portals-pluto/collaborators{/collaborator}",
            "teams_url": "https://api.github.com/repos/apache/portals-pluto/teams",
            "languages_url": "https://api.github.com/repos/apache/portals-pluto/languages",
            "stargazers_url": "https://api.github.com/repos/apache/portals-pluto/stargazers",
            "branches_url": "https://api.github.com/repos/apache/portals-pluto/branches{/branch}",
            "full_name": "apache/portals-pluto",
            "downloads_url": "https://api.github.com/repos/apache/portals-pluto/downloads"
        },
        "html_url": "https://github.com/apache/portals-pluto/commit/078603ffeb3154063e069123df98c842712c9dff",
        "committer": null,
        "sha": "078603ffeb3154063e069123df98c842712c9dff",
        "author": null
    },
    {
        "node_id": "MDY6Q29tbWl0MjAwODk4NjA6MmU3MjU1MDRjMzIyOWVlYmQxMDBiMjdkMjk0MmQyMzc0YzRlYjljNg==",
        "commit": {
            "tree": {
                "sha": "8aff10e2ad97c76d0d2123c65d8517304a8e6467",
                "url": "https://api.github.com/repos/apache/portals-pluto/git/trees/8aff10e2ad97c76d0d2123c65d8517304a8e6467"
            },
            "author": {
                "email": "cdoremus@apache.org",
                "name": "Craig Doremus",
                "date": "2007-12-08T11:12:47.000Z"
            },
            "message": "Copied from trunk to fix NPE at pluto startup\n\ngit-svn-id: https://svn.apache.org/repos/asf/portals/pluto/branches/1.1-286-trunk-merge@602446 13f79535-47bb-0310-9956-ffa450edef68",
            "committer": {
                "email": "cdoremus@apache.org",
                "name": "Craig Doremus",
                "date": "2007-12-08T11:12:47.000Z"
            },
            "url": "https://api.github.com/repos/apache/portals-pluto/git/commits/2e725504c3229eebd100b27d2942d2374c4eb9c6",
            "comment_count": 0
        },
        "parents": [
            {
                "html_url": "https://github.com/apache/portals-pluto/commit/c764edf0dd3a4f48c4272ff613067e82c682c355",
                "sha": "c764edf0dd3a4f48c4272ff613067e82c682c355",
                "url": "https://api.github.com/repos/apache/portals-pluto/commits/c764edf0dd3a4f48c4272ff613067e82c682c355"
            }
        ],
        "score": 8.261887,
        "url": "https://api.github.com/repos/apache/portals-pluto/commits/2e725504c3229eebd100b27d2942d2374c4eb9c6",
        "comments_url": "https://api.github.com/repos/apache/portals-pluto/commits/2e725504c3229eebd100b27d2942d2374c4eb9c6/comments",
        "repository": {
            "git_commits_url": "https://api.github.com/repos/apache/portals-pluto/git/commits{/sha}",
            "blobs_url": "https://api.github.com/repos/apache/portals-pluto/git/blobs{/sha}",
            "tags_url": "https://api.github.com/repos/apache/portals-pluto/tags",
            "fork": false,
            "keys_url": "https://api.github.com/repos/apache/portals-pluto/keys{/key_id}",
            "issues_url": "https://api.github.com/repos/apache/portals-pluto/issues{/number}",
            "commits_url": "https://api.github.com/repos/apache/portals-pluto/commits{/sha}",
            "statuses_url": "https://api.github.com/repos/apache/portals-pluto/statuses/{sha}",
            "notifications_url": "https://api.github.com/repos/apache/portals-pluto/notifications{?since,all,participating}",
            "forks_url": "https://api.github.com/repos/apache/portals-pluto/forks",
            "labels_url": "https://api.github.com/repos/apache/portals-pluto/labels{/name}",
            "contributors_url": "https://api.github.com/repos/apache/portals-pluto/contributors",
            "trees_url": "https://api.github.com/repos/apache/portals-pluto/git/trees{/sha}",
            "merges_url": "https://api.github.com/repos/apache/portals-pluto/merges",
            "contents_url": "https://api.github.com/repos/apache/portals-pluto/contents/{+path}",
            "assignees_url": "https://api.github.com/repos/apache/portals-pluto/assignees{/user}",
            "pulls_url": "https://api.github.com/repos/apache/portals-pluto/pulls{/number}",
            "id": 20089860,
            "owner": {
                "gists_url": "https://api.github.com/users/apache/gists{/gist_id}",
                "following_url": "https://api.github.com/users/apache/following{/other_user}",
                "site_admin": false,
                "gravatar_id": "",
                "events_url": "https://api.github.com/users/apache/events{/privacy}",
                "starred_url": "https://api.github.com/users/apache/starred{/owner}{/repo}",
                "followers_url": "https://api.github.com/users/apache/followers",
                "subscriptions_url": "https://api.github.com/users/apache/subscriptions",
                "organizations_url": "https://api.github.com/users/apache/orgs",
                "id": 47359,
                "node_id": "MDEyOk9yZ2FuaXphdGlvbjQ3MzU5",
                "received_events_url": "https://api.github.com/users/apache/received_events",
                "avatar_url": "https://avatars0.githubusercontent.com/u/47359?v=4",
                "login": "apache",
                "html_url": "https://github.com/apache",
                "type": "Organization",
                "repos_url": "https://api.github.com/users/apache/repos",
                "url": "https://api.github.com/users/apache"
            },
            "private": false,
            "deployments_url": "https://api.github.com/repos/apache/portals-pluto/deployments",
            "name": "portals-pluto",
            "subscription_url": "https://api.github.com/repos/apache/portals-pluto/subscription",
            "git_tags_url": "https://api.github.com/repos/apache/portals-pluto/git/tags{/sha}",
            "description": "Mirror of Apache Pluto",
            "url": "https://api.github.com/repos/apache/portals-pluto",
            "events_url": "https://api.github.com/repos/apache/portals-pluto/events",
            "comments_url": "https://api.github.com/repos/apache/portals-pluto/comments{/number}",
            "issue_comment_url": "https://api.github.com/repos/apache/portals-pluto/issues/comments{/number}",
            "milestones_url": "https://api.github.com/repos/apache/portals-pluto/milestones{/number}",
            "node_id": "MDEwOlJlcG9zaXRvcnkyMDA4OTg2MA==",
            "compare_url": "https://api.github.com/repos/apache/portals-pluto/compare/{base}...{head}",
            "html_url": "https://github.com/apache/portals-pluto",
            "git_refs_url": "https://api.github.com/repos/apache/portals-pluto/git/refs{/sha}",
            "issue_events_url": "https://api.github.com/repos/apache/portals-pluto/issues/events{/number}",
            "hooks_url": "https://api.github.com/repos/apache/portals-pluto/hooks",
            "releases_url": "https://api.github.com/repos/apache/portals-pluto/releases{/id}",
            "archive_url": "https://api.github.com/repos/apache/portals-pluto/{archive_format}{/ref}",
            "subscribers_url": "https://api.github.com/repos/apache/portals-pluto/subscribers",
            "collaborators_url": "https://api.github.com/repos/apache/portals-pluto/collaborators{/collaborator}",
            "teams_url": "https://api.github.com/repos/apache/portals-pluto/teams",
            "languages_url": "https://api.github.com/repos/apache/portals-pluto/languages",
            "stargazers_url": "https://api.github.com/repos/apache/portals-pluto/stargazers",
            "branches_url": "https://api.github.com/repos/apache/portals-pluto/branches{/branch}",
            "full_name": "apache/portals-pluto",
            "downloads_url": "https://api.github.com/repos/apache/portals-pluto/downloads"
        },
        "html_url": "https://github.com/apache/portals-pluto/commit/2e725504c3229eebd100b27d2942d2374c4eb9c6",
        "committer": null,
        "sha": "2e725504c3229eebd100b27d2942d2374c4eb9c6",
        "author": null
    },
    {
        "node_id": "MDY6Q29tbWl0MjAwODk4NjA6M2ZkOGU3N2JhMDA4MzY4ZmNiYjJhZmE5OWUwMDM4ODg5NTkyNGNlOQ==",
        "commit": {
            "tree": {
                "sha": "d6998225831ddc01676e8360f1439fbabb08d640",
                "url": "https://api.github.com/repos/apache/portals-pluto/git/trees/d6998225831ddc01676e8360f1439fbabb08d640"
            },
            "author": {
                "email": "cdoremus@apache.org",
                "name": "Craig Doremus",
                "date": "2007-12-08T11:00:34.000Z"
            },
            "message": "Copied from trunk to fix NPE at pluto startup\n\ngit-svn-id: https://svn.apache.org/repos/asf/portals/pluto/branches/1.1-286-trunk-merge@602444 13f79535-47bb-0310-9956-ffa450edef68",
            "committer": {
                "email": "cdoremus@apache.org",
                "name": "Craig Doremus",
                "date": "2007-12-08T11:00:34.000Z"
            },
            "url": "https://api.github.com/repos/apache/portals-pluto/git/commits/3fd8e77ba008368fcbb2afa99e00388895924ce9",
            "comment_count": 0
        },
        "parents": [
            {
                "html_url": "https://github.com/apache/portals-pluto/commit/abe4fead029df5ce0256ed94b3980373be7893e7",
                "sha": "abe4fead029df5ce0256ed94b3980373be7893e7",
                "url": "https://api.github.com/repos/apache/portals-pluto/commits/abe4fead029df5ce0256ed94b3980373be7893e7"
            }
        ],
        "score": 8.261887,
        "url": "https://api.github.com/repos/apache/portals-pluto/commits/3fd8e77ba008368fcbb2afa99e00388895924ce9",
        "comments_url": "https://api.github.com/repos/apache/portals-pluto/commits/3fd8e77ba008368fcbb2afa99e00388895924ce9/comments",
        "repository": {
            "git_commits_url": "https://api.github.com/repos/apache/portals-pluto/git/commits{/sha}",
            "blobs_url": "https://api.github.com/repos/apache/portals-pluto/git/blobs{/sha}",
            "tags_url": "https://api.github.com/repos/apache/portals-pluto/tags",
            "fork": false,
            "keys_url": "https://api.github.com/repos/apache/portals-pluto/keys{/key_id}",
            "issues_url": "https://api.github.com/repos/apache/portals-pluto/issues{/number}",
            "commits_url": "https://api.github.com/repos/apache/portals-pluto/commits{/sha}",
            "statuses_url": "https://api.github.com/repos/apache/portals-pluto/statuses/{sha}",
            "notifications_url": "https://api.github.com/repos/apache/portals-pluto/notifications{?since,all,participating}",
            "forks_url": "https://api.github.com/repos/apache/portals-pluto/forks",
            "labels_url": "https://api.github.com/repos/apache/portals-pluto/labels{/name}",
            "contributors_url": "https://api.github.com/repos/apache/portals-pluto/contributors",
            "trees_url": "https://api.github.com/repos/apache/portals-pluto/git/trees{/sha}",
            "merges_url": "https://api.github.com/repos/apache/portals-pluto/merges",
            "contents_url": "https://api.github.com/repos/apache/portals-pluto/contents/{+path}",
            "assignees_url": "https://api.github.com/repos/apache/portals-pluto/assignees{/user}",
            "pulls_url": "https://api.github.com/repos/apache/portals-pluto/pulls{/number}",
            "id": 20089860,
            "owner": {
                "gists_url": "https://api.github.com/users/apache/gists{/gist_id}",
                "following_url": "https://api.github.com/users/apache/following{/other_user}",
                "site_admin": false,
                "gravatar_id": "",
                "events_url": "https://api.github.com/users/apache/events{/privacy}",
                "starred_url": "https://api.github.com/users/apache/starred{/owner}{/repo}",
                "followers_url": "https://api.github.com/users/apache/followers",
                "subscriptions_url": "https://api.github.com/users/apache/subscriptions",
                "organizations_url": "https://api.github.com/users/apache/orgs",
                "id": 47359,
                "node_id": "MDEyOk9yZ2FuaXphdGlvbjQ3MzU5",
                "received_events_url": "https://api.github.com/users/apache/received_events",
                "avatar_url": "https://avatars0.githubusercontent.com/u/47359?v=4",
                "login": "apache",
                "html_url": "https://github.com/apache",
                "type": "Organization",
                "repos_url": "https://api.github.com/users/apache/repos",
                "url": "https://api.github.com/users/apache"
            },
            "private": false,
            "deployments_url": "https://api.github.com/repos/apache/portals-pluto/deployments",
            "name": "portals-pluto",
            "subscription_url": "https://api.github.com/repos/apache/portals-pluto/subscription",
            "git_tags_url": "https://api.github.com/repos/apache/portals-pluto/git/tags{/sha}",
            "description": "Mirror of Apache Pluto",
            "url": "https://api.github.com/repos/apache/portals-pluto",
            "events_url": "https://api.github.com/repos/apache/portals-pluto/events",
            "comments_url": "https://api.github.com/repos/apache/portals-pluto/comments{/number}",
            "issue_comment_url": "https://api.github.com/repos/apache/portals-pluto/issues/comments{/number}",
            "milestones_url": "https://api.github.com/repos/apache/portals-pluto/milestones{/number}",
            "node_id": "MDEwOlJlcG9zaXRvcnkyMDA4OTg2MA==",
            "compare_url": "https://api.github.com/repos/apache/portals-pluto/compare/{base}...{head}",
            "html_url": "https://github.com/apache/portals-pluto",
            "git_refs_url": "https://api.github.com/repos/apache/portals-pluto/git/refs{/sha}",
            "issue_events_url": "https://api.github.com/repos/apache/portals-pluto/issues/events{/number}",
            "hooks_url": "https://api.github.com/repos/apache/portals-pluto/hooks",
            "releases_url": "https://api.github.com/repos/apache/portals-pluto/releases{/id}",
            "archive_url": "https://api.github.com/repos/apache/portals-pluto/{archive_format}{/ref}",
            "subscribers_url": "https://api.github.com/repos/apache/portals-pluto/subscribers",
            "collaborators_url": "https://api.github.com/repos/apache/portals-pluto/collaborators{/collaborator}",
            "teams_url": "https://api.github.com/repos/apache/portals-pluto/teams",
            "languages_url": "https://api.github.com/repos/apache/portals-pluto/languages",
            "stargazers_url": "https://api.github.com/repos/apache/portals-pluto/stargazers",
            "branches_url": "https://api.github.com/repos/apache/portals-pluto/branches{/branch}",
            "full_name": "apache/portals-pluto",
            "downloads_url": "https://api.github.com/repos/apache/portals-pluto/downloads"
        },
        "html_url": "https://github.com/apache/portals-pluto/commit/3fd8e77ba008368fcbb2afa99e00388895924ce9",
        "committer": null,
        "sha": "3fd8e77ba008368fcbb2afa99e00388895924ce9",
        "author": null
    },
    {
        "node_id": "MDY6Q29tbWl0MjAwODk4NjA6NGYxODVhNTY2ZTEwZWVmZjZlM2I5YjhjZmY3ZmY5YzBjMTQ2ODc3Ng==",
        "commit": {
            "tree": {
                "sha": "3ba98885032b884579d3ecb06c1b78203c8b3b12",
                "url": "https://api.github.com/repos/apache/portals-pluto/git/trees/3ba98885032b884579d3ecb06c1b78203c8b3b12"
            },
            "author": {
                "email": "ate@apache.org",
                "name": "Ate Douma",
                "date": "2008-10-31T18:05:23.000Z"
            },
            "message": "PLUTO-481 - Pluto 2.0 Refactoring Initiative\nSee: http://issues.apache.org/jira/browse/PLUTO-481\nSeveral small fixes:\n- NPE in PortletPreferencesImpl when no Validator is defined\n- Synchronizing on PortletServlet registration/destroy\n- another JSP tag attribute encoding issue (Tomcat really is not allowing these errors anymore)\n\ngit-svn-id: https://svn.apache.org/repos/asf/portals/pluto/branches/2.0-spi-refactoring@709513 13f79535-47bb-0310-9956-ffa450edef68",
            "committer": {
                "email": "ate@apache.org",
                "name": "Ate Douma",
                "date": "2008-10-31T18:05:23.000Z"
            },
            "url": "https://api.github.com/repos/apache/portals-pluto/git/commits/4f185a566e10eeff6e3b9b8cff7ff9c0c1468776",
            "comment_count": 0
        },
        "parents": [
            {
                "html_url": "https://github.com/apache/portals-pluto/commit/729a195295b9fccf779aaceed3a9dc3df3b13e0e",
                "sha": "729a195295b9fccf779aaceed3a9dc3df3b13e0e",
                "url": "https://api.github.com/repos/apache/portals-pluto/commits/729a195295b9fccf779aaceed3a9dc3df3b13e0e"
            }
        ],
        "score": 6.1652126,
        "url": "https://api.github.com/repos/apache/portals-pluto/commits/4f185a566e10eeff6e3b9b8cff7ff9c0c1468776",
        "comments_url": "https://api.github.com/repos/apache/portals-pluto/commits/4f185a566e10eeff6e3b9b8cff7ff9c0c1468776/comments",
        "repository": {
            "git_commits_url": "https://api.github.com/repos/apache/portals-pluto/git/commits{/sha}",
            "blobs_url": "https://api.github.com/repos/apache/portals-pluto/git/blobs{/sha}",
            "tags_url": "https://api.github.com/repos/apache/portals-pluto/tags",
            "fork": false,
            "keys_url": "https://api.github.com/repos/apache/portals-pluto/keys{/key_id}",
            "issues_url": "https://api.github.com/repos/apache/portals-pluto/issues{/number}",
            "commits_url": "https://api.github.com/repos/apache/portals-pluto/commits{/sha}",
            "statuses_url": "https://api.github.com/repos/apache/portals-pluto/statuses/{sha}",
            "notifications_url": "https://api.github.com/repos/apache/portals-pluto/notifications{?since,all,participating}",
            "forks_url": "https://api.github.com/repos/apache/portals-pluto/forks",
            "labels_url": "https://api.github.com/repos/apache/portals-pluto/labels{/name}",
            "contributors_url": "https://api.github.com/repos/apache/portals-pluto/contributors",
            "trees_url": "https://api.github.com/repos/apache/portals-pluto/git/trees{/sha}",
            "merges_url": "https://api.github.com/repos/apache/portals-pluto/merges",
            "contents_url": "https://api.github.com/repos/apache/portals-pluto/contents/{+path}",
            "assignees_url": "https://api.github.com/repos/apache/portals-pluto/assignees{/user}",
            "pulls_url": "https://api.github.com/repos/apache/portals-pluto/pulls{/number}",
            "id": 20089860,
            "owner": {
                "gists_url": "https://api.github.com/users/apache/gists{/gist_id}",
                "following_url": "https://api.github.com/users/apache/following{/other_user}",
                "site_admin": false,
                "gravatar_id": "",
                "events_url": "https://api.github.com/users/apache/events{/privacy}",
                "starred_url": "https://api.github.com/users/apache/starred{/owner}{/repo}",
                "followers_url": "https://api.github.com/users/apache/followers",
                "subscriptions_url": "https://api.github.com/users/apache/subscriptions",
                "organizations_url": "https://api.github.com/users/apache/orgs",
                "id": 47359,
                "node_id": "MDEyOk9yZ2FuaXphdGlvbjQ3MzU5",
                "received_events_url": "https://api.github.com/users/apache/received_events",
                "avatar_url": "https://avatars0.githubusercontent.com/u/47359?v=4",
                "login": "apache",
                "html_url": "https://github.com/apache",
                "type": "Organization",
                "repos_url": "https://api.github.com/users/apache/repos",
                "url": "https://api.github.com/users/apache"
            },
            "private": false,
            "deployments_url": "https://api.github.com/repos/apache/portals-pluto/deployments",
            "name": "portals-pluto",
            "subscription_url": "https://api.github.com/repos/apache/portals-pluto/subscription",
            "git_tags_url": "https://api.github.com/repos/apache/portals-pluto/git/tags{/sha}",
            "description": "Mirror of Apache Pluto",
            "url": "https://api.github.com/repos/apache/portals-pluto",
            "events_url": "https://api.github.com/repos/apache/portals-pluto/events",
            "comments_url": "https://api.github.com/repos/apache/portals-pluto/comments{/number}",
            "issue_comment_url": "https://api.github.com/repos/apache/portals-pluto/issues/comments{/number}",
            "milestones_url": "https://api.github.com/repos/apache/portals-pluto/milestones{/number}",
            "node_id": "MDEwOlJlcG9zaXRvcnkyMDA4OTg2MA==",
            "compare_url": "https://api.github.com/repos/apache/portals-pluto/compare/{base}...{head}",
            "html_url": "https://github.com/apache/portals-pluto",
            "git_refs_url": "https://api.github.com/repos/apache/portals-pluto/git/refs{/sha}",
            "issue_events_url": "https://api.github.com/repos/apache/portals-pluto/issues/events{/number}",
            "hooks_url": "https://api.github.com/repos/apache/portals-pluto/hooks",
            "releases_url": "https://api.github.com/repos/apache/portals-pluto/releases{/id}",
            "archive_url": "https://api.github.com/repos/apache/portals-pluto/{archive_format}{/ref}",
            "subscribers_url": "https://api.github.com/repos/apache/portals-pluto/subscribers",
            "collaborators_url": "https://api.github.com/repos/apache/portals-pluto/collaborators{/collaborator}",
            "teams_url": "https://api.github.com/repos/apache/portals-pluto/teams",
            "languages_url": "https://api.github.com/repos/apache/portals-pluto/languages",
            "stargazers_url": "https://api.github.com/repos/apache/portals-pluto/stargazers",
            "branches_url": "https://api.github.com/repos/apache/portals-pluto/branches{/branch}",
            "full_name": "apache/portals-pluto",
            "downloads_url": "https://api.github.com/repos/apache/portals-pluto/downloads"
        },
        "html_url": "https://github.com/apache/portals-pluto/commit/4f185a566e10eeff6e3b9b8cff7ff9c0c1468776",
        "committer": {
            "gists_url": "https://api.github.com/users/ate/gists{/gist_id}",
            "following_url": "https://api.github.com/users/ate/following{/other_user}",
            "site_admin": false,
            "gravatar_id": "",
            "events_url": "https://api.github.com/users/ate/events{/privacy}",
            "starred_url": "https://api.github.com/users/ate/starred{/owner}{/repo}",
            "followers_url": "https://api.github.com/users/ate/followers",
            "subscriptions_url": "https://api.github.com/users/ate/subscriptions",
            "organizations_url": "https://api.github.com/users/ate/orgs",
            "id": 1111320,
            "node_id": "MDQ6VXNlcjExMTEzMjA=",
            "received_events_url": "https://api.github.com/users/ate/received_events",
            "avatar_url": "https://avatars2.githubusercontent.com/u/1111320?v=4",
            "login": "ate",
            "html_url": "https://github.com/ate",
            "type": "User",
            "repos_url": "https://api.github.com/users/ate/repos",
            "url": "https://api.github.com/users/ate"
        },
        "sha": "4f185a566e10eeff6e3b9b8cff7ff9c0c1468776",
        "author": {
            "gists_url": "https://api.github.com/users/ate/gists{/gist_id}",
            "following_url": "https://api.github.com/users/ate/following{/other_user}",
            "site_admin": false,
            "gravatar_id": "",
            "events_url": "https://api.github.com/users/ate/events{/privacy}",
            "starred_url": "https://api.github.com/users/ate/starred{/owner}{/repo}",
            "followers_url": "https://api.github.com/users/ate/followers",
            "subscriptions_url": "https://api.github.com/users/ate/subscriptions",
            "organizations_url": "https://api.github.com/users/ate/orgs",
            "id": 1111320,
            "node_id": "MDQ6VXNlcjExMTEzMjA=",
            "received_events_url": "https://api.github.com/users/ate/received_events",
            "avatar_url": "https://avatars2.githubusercontent.com/u/1111320?v=4",
            "login": "ate",
            "html_url": "https://github.com/ate",
            "type": "User",
            "repos_url": "https://api.github.com/users/ate/repos",
            "url": "https://api.github.com/users/ate"
        }
    },
    {
        "node_id": "MDY6Q29tbWl0MjAwODk4NjA6NDNmZGE4YTBmNDg0ZTM2MTY2OGJkMGJmN2Q0Zjc5ODE1OTEzMDYyMA==",
        "commit": {
            "tree": {
                "sha": "47c72a22e06eefb76c9fe22d74df5adae47ba1d4",
                "url": "https://api.github.com/repos/apache/portals-pluto/git/trees/47c72a22e06eefb76c9fe22d74df5adae47ba1d4"
            },
            "author": {
                "email": "taylor@apache.org",
                "name": "David Sean Taylor",
                "date": "2004-04-07T03:40:34.000Z"
            },
            "message": "found this bug in J2, was causing Tomcat to NPE\n\nPR:\nObtained from:\nSubmitted by:\t\nReviewed by:\t\nCVS: ----------------------------------------------------------------------\nCVS: PR:\nCVS:   If this change addresses a PR in the problem report tracking\nCVS:   database, then enter the PR number(s) here.\nCVS: Obtained from:\nCVS:   If this change has been taken from another system, such as NCSA,\nCVS:   then name the system in this line, otherwise delete it.\nCVS: Submitted by:\nCVS:   If this code has been contributed to Apache by someone else; i.e.,\nCVS:   they sent us a patch or a new module, then include their name/email\nCVS:   address here. If this is your work then delete this line.\nCVS: Reviewed by:\nCVS:   If we are doing pre-commit code reviews and someone else has\nCVS:   reviewed your changes, include their name(s) here.\nCVS:   If you have not had it reviewed then delete this line.\n\n\ngit-svn-id: https://svn.apache.org/repos/asf/portals/pluto/trunk@35962 13f79535-47bb-0310-9956-ffa450edef68",
            "committer": {
                "email": "taylor@apache.org",
                "name": "David Sean Taylor",
                "date": "2004-04-07T03:40:34.000Z"
            },
            "url": "https://api.github.com/repos/apache/portals-pluto/git/commits/43fda8a0f484e361668bd0bf7d4f798159130620",
            "comment_count": 0
        },
        "parents": [
            {
                "html_url": "https://github.com/apache/portals-pluto/commit/34b5a8dc1c4756876bd21801e0558c12c4d8d710",
                "sha": "34b5a8dc1c4756876bd21801e0558c12c4d8d710",
                "url": "https://api.github.com/repos/apache/portals-pluto/commits/34b5a8dc1c4756876bd21801e0558c12c4d8d710"
            }
        ],
        "score": 3.0353568,
        "url": "https://api.github.com/repos/apache/portals-pluto/commits/43fda8a0f484e361668bd0bf7d4f798159130620",
        "comments_url": "https://api.github.com/repos/apache/portals-pluto/commits/43fda8a0f484e361668bd0bf7d4f798159130620/comments",
        "repository": {
            "git_commits_url": "https://api.github.com/repos/apache/portals-pluto/git/commits{/sha}",
            "blobs_url": "https://api.github.com/repos/apache/portals-pluto/git/blobs{/sha}",
            "tags_url": "https://api.github.com/repos/apache/portals-pluto/tags",
            "fork": false,
            "keys_url": "https://api.github.com/repos/apache/portals-pluto/keys{/key_id}",
            "issues_url": "https://api.github.com/repos/apache/portals-pluto/issues{/number}",
            "commits_url": "https://api.github.com/repos/apache/portals-pluto/commits{/sha}",
            "statuses_url": "https://api.github.com/repos/apache/portals-pluto/statuses/{sha}",
            "notifications_url": "https://api.github.com/repos/apache/portals-pluto/notifications{?since,all,participating}",
            "forks_url": "https://api.github.com/repos/apache/portals-pluto/forks",
            "labels_url": "https://api.github.com/repos/apache/portals-pluto/labels{/name}",
            "contributors_url": "https://api.github.com/repos/apache/portals-pluto/contributors",
            "trees_url": "https://api.github.com/repos/apache/portals-pluto/git/trees{/sha}",
            "merges_url": "https://api.github.com/repos/apache/portals-pluto/merges",
            "contents_url": "https://api.github.com/repos/apache/portals-pluto/contents/{+path}",
            "assignees_url": "https://api.github.com/repos/apache/portals-pluto/assignees{/user}",
            "pulls_url": "https://api.github.com/repos/apache/portals-pluto/pulls{/number}",
            "id": 20089860,
            "owner": {
                "gists_url": "https://api.github.com/users/apache/gists{/gist_id}",
                "following_url": "https://api.github.com/users/apache/following{/other_user}",
                "site_admin": false,
                "gravatar_id": "",
                "events_url": "https://api.github.com/users/apache/events{/privacy}",
                "starred_url": "https://api.github.com/users/apache/starred{/owner}{/repo}",
                "followers_url": "https://api.github.com/users/apache/followers",
                "subscriptions_url": "https://api.github.com/users/apache/subscriptions",
                "organizations_url": "https://api.github.com/users/apache/orgs",
                "id": 47359,
                "node_id": "MDEyOk9yZ2FuaXphdGlvbjQ3MzU5",
                "received_events_url": "https://api.github.com/users/apache/received_events",
                "avatar_url": "https://avatars0.githubusercontent.com/u/47359?v=4",
                "login": "apache",
                "html_url": "https://github.com/apache",
                "type": "Organization",
                "repos_url": "https://api.github.com/users/apache/repos",
                "url": "https://api.github.com/users/apache"
            },
            "private": false,
            "deployments_url": "https://api.github.com/repos/apache/portals-pluto/deployments",
            "name": "portals-pluto",
            "subscription_url": "https://api.github.com/repos/apache/portals-pluto/subscription",
            "git_tags_url": "https://api.github.com/repos/apache/portals-pluto/git/tags{/sha}",
            "description": "Mirror of Apache Pluto",
            "url": "https://api.github.com/repos/apache/portals-pluto",
            "events_url": "https://api.github.com/repos/apache/portals-pluto/events",
            "comments_url": "https://api.github.com/repos/apache/portals-pluto/comments{/number}",
            "issue_comment_url": "https://api.github.com/repos/apache/portals-pluto/issues/comments{/number}",
            "milestones_url": "https://api.github.com/repos/apache/portals-pluto/milestones{/number}",
            "node_id": "MDEwOlJlcG9zaXRvcnkyMDA4OTg2MA==",
            "compare_url": "https://api.github.com/repos/apache/portals-pluto/compare/{base}...{head}",
            "html_url": "https://github.com/apache/portals-pluto",
            "git_refs_url": "https://api.github.com/repos/apache/portals-pluto/git/refs{/sha}",
            "issue_events_url": "https://api.github.com/repos/apache/portals-pluto/issues/events{/number}",
            "hooks_url": "https://api.github.com/repos/apache/portals-pluto/hooks",
            "releases_url": "https://api.github.com/repos/apache/portals-pluto/releases{/id}",
            "archive_url": "https://api.github.com/repos/apache/portals-pluto/{archive_format}{/ref}",
            "subscribers_url": "https://api.github.com/repos/apache/portals-pluto/subscribers",
            "collaborators_url": "https://api.github.com/repos/apache/portals-pluto/collaborators{/collaborator}",
            "teams_url": "https://api.github.com/repos/apache/portals-pluto/teams",
            "languages_url": "https://api.github.com/repos/apache/portals-pluto/languages",
            "stargazers_url": "https://api.github.com/repos/apache/portals-pluto/stargazers",
            "branches_url": "https://api.github.com/repos/apache/portals-pluto/branches{/branch}",
            "full_name": "apache/portals-pluto",
            "downloads_url": "https://api.github.com/repos/apache/portals-pluto/downloads"
        },
        "html_url": "https://github.com/apache/portals-pluto/commit/43fda8a0f484e361668bd0bf7d4f798159130620",
        "committer": null,
        "sha": "43fda8a0f484e361668bd0bf7d4f798159130620",
        "author": null
    }
]